CHANGES.txt
LICENSE
MANIFEST.in
README.rst
requirements.txt
setup.py
didel/__init__.py
didel/base.py
didel/cli.py
didel/config.py
didel/courses.py
didel/exceptions.py
didel/fileutils.py
didel/session.py
didel/souputils.py
didel/student.py
didelcli.egg-info/PKG-INFO
didelcli.egg-info/SOURCES.txt
didelcli.egg-info/dependency_links.txt
didelcli.egg-info/entry_points.txt
didelcli.egg-info/requires.txt
didelcli.egg-info/top_level.txt