Metadata-Version: 1.1
Name: didelcli
Version: 0.1.2
Summary: Didel command-line tool
Home-page: https://github.com/bfontaine/didelcli
Author: Baptiste Fontaine
Author-email: b@ptistefontaine.fr
License: Copyright © 2014-2015 – Baptiste Fontaine
